LICENSE
MANIFEST.in
ReadMe.md
setup.cfg
setup.py
manipuldate/__init__.py
manipuldate/enums.py
manipuldate/manipuldate.py
manipuldate.egg-info/PKG-INFO
manipuldate.egg-info/SOURCES.txt
manipuldate.egg-info/dependency_links.txt
manipuldate.egg-info/requires.txt
manipuldate.egg-info/top_level.txt