Metadata-Version: 1.1
Name: manipuldate
Version: 0.2.0
Summary: Date/Time/DateTime Manipulation Done Right
Home-page: https://github.com/JenkinsDev/manipuldate
Author: David Jenkins
Author-email: david.nicholas.jenkins@gmail.com
License: MIT
Platform: UNKNOWN
Classifier: Development Status :: 4 - Beta
Classifier: Intended Audience :: Developers
Classifier: Natural Language :: English
Classifier: License :: OSI Approved :: MIT License
Classifier: Operating System :: OS Independent
Classifier: Programming Language :: Python
Classifier: Programming Language :: Python :: 3
Classifier: Programming Language :: Python :: 3.2
Classifier: Programming Language :: Python :: 3.3
Classifier: Programming Language :: Python :: 3.4
Classifier: Topic :: Software Development :: Libraries :: Python Modules
